{
  "headers": {
    "x-amz-cf-pop": "HEL51-P2",
    "last-modified": "Fri, 25 Mar 2022 13:32:49 GMT",
    "date": "Sun, 25 Sep 2022 21:03:59 GMT",
    "x-amz-cf-id": "9sf_NVXtPrBLtaCjfNSnNM6aO562hWnKkFPBQyMC2b2mMMOpy41pxw==",
    "server": "deno/gcp-europe-north1",
    "cache-control": "public, max-age=31536000, immutable",
    "x-cache": "Hit from cloudfront",
    "accept-ranges": "bytes",
    "content-length": "1737",
    "vary": "Accept-Encoding, Origin",
    "x-amz-replication-status": "FAILED",
    "access-control-allow-origin": "*",
    "etag": "\"5cc41350bd6a078448fc39f24d027a3d\"",
    "age": "9923732",
    "content-type": "application/typescript; charset=utf-8",
    "content-security-policy": "default-src 'none'; style-src 'unsafe-inline'; sandbox",
    "x-amz-version-id": "83urVXc47viVXD7rXb0NlkKwHY6wPm3X",
    "via": "http/2 edgeproxy-h"
  },
  "url": "https://deno.land/std@0.132.0/node/_options.ts",
  "now": {
    "secs_since_epoch": 1674063571,
    "nanos_since_epoch": 405130598
  }
}