{
  "headers": {
    "server-timing": "attempt;val=1,cdn-cache-hit,cdn-pop;desc=\"HEL51-P2\",cdn-rid;desc=\"fS99163Vpl48aHFSvlzdP95bNUyQeC2XaB05JB3iQLSYapTsCdFEUw==\",cdn-hit-layer;desc=\"EDGE\",cdn-downstream-fbl;dur=1, fetchSource;dur=60",
    "content-security-policy": "default-src 'none'; style-src 'unsafe-inline'; sandbox",
    "last-modified": "Fri, 25 Mar 2022 13:32:48 GMT",
    "referrer-policy": "strict-origin-when-cross-origin",
    "access-control-allow-origin": "*",
    "x-frame-options": "DENY",
    "x-amz-cf-id": "fS99163Vpl48aHFSvlzdP95bNUyQeC2XaB05JB3iQLSYapTsCdFEUw==",
    "cross-origin-opener-policy": "same-origin",
    "strict-transport-security": "max-age=63072000; includeSubDomains; preload",
    "x-amz-version-id": "oNbIbIZtb1xw4ZN3sY1TRW_wI2Jc6l5i",
    "etag": "W/\"93d3247a09c9d9c74e2ad48c68ad61bb\"",
    "via": "http/2 edgeproxy-h",
    "x-content-type-options": "nosniff",
    "cross-origin-embedder-policy": "same-origin",
    "x-amz-cf-pop": "HEL51-P2",
    "content-type": "application/javascript",
    "date": "Fri, 26 May 2023 13:26:29 GMT",
    "age": "68391",
    "x-amz-replication-status": "COMPLETED",
    "x-cache": "Hit from cloudfront",
    "vary": "Accept-Encoding, Origin",
    "cache-control": "public, max-age=31536000, immutable",
    "server": "deno/gcp-europe-north1",
    "cross-origin-resource-policy": "same-origin"
  },
  "url": "https://deno.land/std@0.132.0/node/_events.mjs",
  "now": {
    "secs_since_epoch": 1685175979,
    "nanos_since_epoch": 171380654
  }
}