{
  "headers": {
    "via": "http/2 edgeproxy-h",
    "access-control-allow-origin": "*",
    "age": "3178552",
    "referrer-policy": "strict-origin-when-cross-origin",
    "x-amz-replication-status": "COMPLETED",
    "server-timing": "attempt;val=1,cdn-cache-hit,cdn-pop;desc=\"HEL51-P2\",cdn-rid;desc=\"tio9lZ6iG-2vbVLh--vNTj4jRR6bt8Qf0SG7yhHBJfszKMk_WWbSZg==\",cdn-hit-layer;desc=\"EDGE\",cdn-downstream-fbl;dur=2, fetchSource;dur=48",
    "x-frame-options": "DENY",
    "strict-transport-security": "max-age=63072000; includeSubDomains; preload",
    "x-amz-version-id": "t7hDN1eVRlNuG2cR_hndG6unK2VN9Au_",
    "x-cache": "Hit from cloudfront",
    "cross-origin-resource-policy": "same-origin",
    "content-type": "application/typescript; charset=utf-8",
    "server": "deno/gcp-europe-north1",
    "vary": "Accept-Encoding, Origin",
    "x-content-type-options": "nosniff",
    "x-amz-cf-pop": "HEL51-P2",
    "last-modified": "Fri, 25 Mar 2022 13:32:47 GMT",
    "date": "Thu, 20 Apr 2023 13:30:28 GMT",
    "content-length": "322",
    "content-security-policy": "default-src 'none'; style-src 'unsafe-inline'; sandbox",
    "etag": "\"dd60e4178a864a90649b4c18f9df4b0e\"",
    "accept-ranges": "bytes",
    "cross-origin-embedder-policy": "same-origin",
    "cross-origin-opener-policy": "same-origin",
    "x-amz-cf-id": "tio9lZ6iG-2vbVLh--vNTj4jRR6bt8Qf0SG7yhHBJfszKMk_WWbSZg==",
    "cache-control": "public, max-age=31536000, immutable"
  },
  "url": "https://deno.land/std@0.132.0/async/mod.ts",
  "now": {
    "secs_since_epoch": 1685175979,
    "nanos_since_epoch": 108708220
  }
}